planning/__init__.py
planning/core/__init__.py
planning-0.0.1.dist-info/LICENSE
planning-0.0.1.dist-info/METADATA
planning-0.0.1.dist-info/WHEEL
planning-0.0.1.dist-info/top_level.txt
planning-0.0.1.dist-info/RECORD
