Metadata-Version: 2.1
Name: planning
Version: 0.0.1
Summary: Planning algorithms
Home-page: https://github.com/brean/python-planning
Author: Andreas Bresser
License: BSD-3
Platform: UNKNOWN
